smoothtable/__init__.py
smoothtable/color_condition.py
smoothtable/constants.py
smoothtable/extra_variable.py
smoothtable/painter.py
smoothtable/table.py
smoothtable/table_style.py
smoothtable/utils.py
smoothtable-0.0.1.dist-info/METADATA
smoothtable-0.0.1.dist-info/WHEEL
smoothtable-0.0.1.dist-info/top_level.txt
smoothtable-0.0.1.dist-info/RECORD
