Metadata-Version: 2.1
Name: smoothtable
Version: 0.0.1
Summary: User-friendly looking table creator.
Home-page: https://github.com/kamillenczewski/smoothtable
Author: Kamil Lenczewski
Author-email: kamillenczewski2@gmail.com
Keywords: smooth table display color
